dcrx_api/__init__.py
dcrx_api/app.py
dcrx_api/lifespan.py
dcrx_api/cli/__init__.py
dcrx_api/cli/base.py
dcrx_api/cli/database.py
dcrx_api/cli/server.py
dcrx_api/context/__init__.py
dcrx_api/context/manager.py
dcrx_api/context/types.py
dcrx_api/database/__init__.py
dcrx_api/database/connection.py
dcrx_api/database/connection_config.py
dcrx_api/database/table_types.py
dcrx_api/database/models/__init__.py
dcrx_api/database/models/database_transaction_result.py
dcrx_api/env/__init__.py
dcrx_api/env/env.py
dcrx_api/env/load_env.py
dcrx_api/env/time_parser.py
dcrx_api/middleware/__init__.py
dcrx_api/middleware/auth_middleware.py
dcrx_api/services/__init__.py
dcrx_api/services/auth/__init__.py
dcrx_api/services/auth/context.py
dcrx_api/services/auth/manager.py
dcrx_api/services/auth/models/__init__.py
dcrx_api/services/auth/models/auth_claims.py
dcrx_api/services/auth/models/auth_response.py
dcrx_api/services/auth/models/authentication_failure_exception.py
dcrx_api/services/auth/models/generated_token.py
dcrx_api/services/jobs/__init__.py
dcrx_api/services/jobs/connection.py
dcrx_api/services/jobs/context.py
dcrx_api/services/jobs/job.py
dcrx_api/services/jobs/queue.py
dcrx_api/services/jobs/service.py
dcrx_api/services/jobs/status.py
dcrx_api/services/jobs/models/__init__.py
dcrx_api/services/jobs/models/build_options.py
dcrx_api/services/jobs/models/image_stats.py
dcrx_api/services/jobs/models/job_metadata.py
dcrx_api/services/jobs/models/job_not_found_exception.py
dcrx_api/services/jobs/models/job_registry.py
dcrx_api/services/jobs/models/job_step_result.py
dcrx_api/services/jobs/models/new_image.py
dcrx_api/services/jobs/models/remote_add.py
dcrx_api/services/jobs/models/server_limit_exception.py
dcrx_api/services/jobs/table/__init__.py
dcrx_api/services/jobs/table/jobs_mysql_table.py
dcrx_api/services/jobs/table/jobs_postgres_table.py
dcrx_api/services/jobs/table/jobs_sqlite_table.py
dcrx_api/services/jobs/table/jobs_table.py
dcrx_api/services/monitoring/__init__.py
dcrx_api-0.4.1.dist-info/LICENSE
dcrx_api-0.4.1.dist-info/METADATA
dcrx_api-0.4.1.dist-info/WHEEL
dcrx_api-0.4.1.dist-info/entry_points.txt
dcrx_api-0.4.1.dist-info/top_level.txt
dcrx_api-0.4.1.dist-info/RECORD
