Metadata-Version: 2.1
Name: dcrx-api
Version: 0.4.1
Summary: A RESTful implementation of the DCRX Docker library.
Home-page: https://github.com/scorbettUM/dcrx-api
Author: Sean Corbett
Author-email: sean.corbett@umontana.edu
Keywords: pypi,cicd,python,setup,docker,infra,devops,fastapi
Classifier: Programming Language :: Python :: 3.8
Classifier: Programming Language :: Python :: 3.9
Classifier: Programming Language :: Python :: 3.10
Classifier: Programming Language :: Python :: 3.11
Classifier: License :: OSI Approved :: MIT License
Classifier: Operating System :: OS Independent
Requires-Python: >=3.10
License-File: LICENSE
Requires-Dist: dcrx
Requires-Dist: fastapi[all]
Requires-Dist: docker
Requires-Dist: psutil
Requires-Dist: python-jose[cryptography]
Requires-Dist: passlib[bcrypt]
Requires-Dist: python-dotenv
Requires-Dist: click
Requires-Dist: uvicorn[standard]
